setup.py
easyFunctionz/__init__.py
easyFunctionz/easyFunctionz.py
easyFunctionz.egg-info/PKG-INFO
easyFunctionz.egg-info/SOURCES.txt
easyFunctionz.egg-info/dependency_links.txt
easyFunctionz.egg-info/top_level.txt