Metadata-Version: 2.1
Name: easyFunctionz
Version: 0.0.2
Summary: to make Functions easy
Home-page: UNKNOWN
Author: Jonathan
Author-email: 
License: UNKNOWN
Keywords: python,easyFunctions,Functions,Function,easy
Platform: UNKNOWN
